{
  "title": "evidences",
  "x-stoplight": {
    "id": "zhi0xcwrlh4lw"
  },
  "type": "object",
  "properties": {
    "id": {
      "type": "string",
      "x-stoplight": {
        "id": "2yljzunmvz3mh"
      }
    },
    "title": {
      "type": "string",
      "x-stoplight": {
        "id": "mhj2b7b7yt5bj"
      }
    },
    "description": {
      "type": "string",
      "x-stoplight": {
        "id": "790p9xie6xoru"
      }
    },
    "relatedDocument": {
      "type": "object",
      "x-stoplight": {
        "id": "az2au8m8avq3x"
      },
      "properties": {
        "id": {
          "type": "string",
          "x-stoplight": {
            "id": "6zqx2slfrd1ao"
          }
        }
      },
      "required": [
        "id"
      ]
    }
  },
  "required": [
    "id",
    "title"
  ],
  "description": "evidences without date"
}